.hgignore
.hgtags
CHANGES.txt
LICENSE.txt
MANIFEST.in
README.txt
bootstrap.py
buildout.cfg
setup.py
js/__init__.py
js.ember.egg-info/PKG-INFO
js.ember.egg-info/SOURCES.txt
js.ember.egg-info/dependency_links.txt
js.ember.egg-info/entry_points.txt
js.ember.egg-info/namespace_packages.txt
js.ember.egg-info/not-zip-safe
js.ember.egg-info/requires.txt
js.ember.egg-info/top_level.txt
js/ember/__init__.py
js/ember/test_ember.txt
js/ember/resources/ember-1.0.0-rc.8.js
js/ember/resources/ember-1.0.0-rc.8.min.js
js/ember/resources/ember-data-0.13-108.js
js/ember/resources/ember-data-0.13-108.min.js
js/ember/resources/handlebars-1.0.0.js
js/ember/resources/handlebars-1.0.0.min.js