Metadata-Version: 1.0
Name: js.ember
Version: 1.0.0-pre.8
Summary: fanstatic ember.js.
Home-page: UNKNOWN
Author: Fanstatic Developers
Author-email: fanstatic@googlegroups.com
License: BSD
Platform: UNKNOWN
